access_select2/__init__.py
access_select2/forms.py
access_select2/models.py
access_select2/urls.py
access_select2/views.py
django_access_select2-0.0.1b1.dist-info/DESCRIPTION.rst
django_access_select2-0.0.1b1.dist-info/METADATA
django_access_select2-0.0.1b1.dist-info/RECORD
django_access_select2-0.0.1b1.dist-info/WHEEL
django_access_select2-0.0.1b1.dist-info/metadata.json
django_access_select2-0.0.1b1.dist-info/top_level.txt
