Metadata-Version: 2.0
Name: django-access-select2
Version: 0.0.1b1
Summary: Django-Access-Select2 - the application providing a default filtering for the Django-Select2 package using Django-Access package
Home-page: https://github.com/nnseva/django-access-select2
Author: Vsevolod Novikov
Author-email: nnseva@gmail.com
License: LGPL
Keywords: select2 access django permissions instance-level row-level django-access authority guard dynamic evaluation evaluation-based runtime rights rights-management
Platform: any
Classifier: Development Status :: 4 - Beta
Classifier: Intended Audience :: Developers
Classifier: Topic :: Software Development :: Libraries
Classifier: Environment :: Web Environment
Classifier: Framework :: Django
Classifier: Framework :: Django :: 1.10
Classifier: Framework :: Django :: 1.11
Classifier: License :: OSI Approved :: GNU Library or Lesser General Public License (LGPL)
Classifier: Programming Language :: Python :: 2
Classifier: Programming Language :: Python :: 2.7
Classifier: Programming Language :: Python :: 3
Classifier: Programming Language :: Python :: 3.4
Classifier: Programming Language :: Python :: 3.5
Requires-Dist: django-select2
Requires-Dist: django-access
